{
  "indexes": [
    {
      "collectionGroup": "activities",
      "queryScope": "COLLECTION",
      "fields": [
        { "fieldPath": "date", "order": "DESCENDING" },
        { "fieldPath": "category", "order": "ASCENDING" }
      ]
    },
    {
      "collectionGroup": "activities",
      "queryScope": "COLLECTION",
      "fields": [
        { "fieldPath": "timestamp", "order": "DESCENDING" },
        { "fieldPath": "co2kg", "order": "DESCENDING" }
      ]
    },
    {
      "collectionGroup": "activities",
      "queryScope": "COLLECTION",
      "fields": [
        { "fieldPath": "date", "order": "ASCENDING" },
        { "fieldPath": "timestamp", "order": "DESCENDING" }
      ]
    },
    {
      "collectionGroup": "leaderboard",
      "queryScope": "COLLECTION",
      "fields": [
        { "fieldPath": "weekId", "order": "ASCENDING" },
        { "fieldPath": "weeklyKg", "order": "ASCENDING" }
      ]
    }
  ],
  "fieldOverrides": []
}
